templtest/__init__.py
templtest/__main__.py
templtest/cli.py
templtest/discovery.py
templtest/exception.py
templtest/template.py
templtest/test.py
templtest-0.3.1.dist-info/METADATA
templtest-0.3.1.dist-info/entry_points.txt
templtest-0.3.1.dist-info/WHEEL
templtest-0.3.1.dist-info/COPYING
templtest-0.3.1.dist-info/RECORD
